__init__.py
downloadit/__init__.py
downloadit/app.py
downloadit/constances.py
downloadit/exceptions.py
downloadit/logs.py
downloadit/models/__init__.py
downloadit/models/app_model.py
downloadit-1.0.0.dist-info/LICENSE
downloadit-1.0.0.dist-info/METADATA
downloadit-1.0.0.dist-info/WHEEL
downloadit-1.0.0.dist-info/top_level.txt
downloadit-1.0.0.dist-info/RECORD
