Metadata-Version: 2.1
Name: downloadit
Version: 1.0.0
Summary: An asynchronous library to download.
Author-email: Alireza Garousi <alireza7948@gmail.com>
Project-URL: Documentation, https://github.com/Alirezagrs
Project-URL: Repository, https://github.com/Alirezagrs/downloadit
Classifier: Programming Language :: Python :: 3
Classifier: License :: OSI Approved :: MIT License
Classifier: Operating System :: OS Independent
Requires-Python: >=3.9
License-File: LICENSE
Requires-Dist: aiohttp ==3.9.5
Requires-Dist: aiofiles ==23.2.1
Requires-Dist: alembic ==1.13.1
Requires-Dist: SQLAlchemy ==2.0.30
Requires-Dist: tqdm ==4.66.4
Provides-Extra: test
Requires-Dist: black ==24.4.2 ; extra == 'test'
